equibatch.py
equibatch-0.1.3.dist-info/METADATA
equibatch-0.1.3.dist-info/WHEEL
equibatch-0.1.3.dist-info/RECORD
