Metadata-Version: 2.3
Name: equibatch
Version: 0.1.3
Summary: Equiareal batch sampler
License: MIT
Author: Vadim Liventsev
Author-email: dev@vadim.me
Requires-Python: >=3.10,<4.0
Classifier: License :: OSI Approved :: MIT License
Classifier: Programming Language :: Python :: 3
Classifier: Programming Language :: Python :: 3.10
Classifier: Programming Language :: Python :: 3.11
Classifier: Programming Language :: Python :: 3.12
Classifier: Programming Language :: Python :: 3.13
